{"stat.useItem.139":2,"stat.useItem.66":4,"stat.useItem.174":38,"stat.killEntity.Ghast":1,"stat.useItem.3":702,"stat.useItem.65":5,"achievement.exploreAllBiomes":{"value":0,"progress":["Forest","Desert","JungleHills","Taiga","Extreme Hills","TaigaHills","Plains","Jungle","Extreme Hills Edge","River","Swampland","Hell"]},"stat.useItem.324":16,"stat.useItem.24":152,"stat.useItem.53":3,"stat.useItem.420":11,"stat.useItem.46":1442,"achievement.openInventory":169,"stat.damageDealt":5535,"stat.useItem.19":268,"stat.useItem.50":793,"stat.useItem.259":131,"stat.useItem.49":14,"stat.killEntity.Cow":2,"stat.useItem.323":4,"stat.useItem.5":1598,"stat.useItem.355":34,"stat.flyOneCm":3316078,"stat.useItem.152":4,"stat.useItem.69":7,"stat.pigOneCm":21706,"stat.climbOneCm":4521,"stat.useItem.45":44,"stat.drop":406,"stat.damageTaken":1640,"stat.useItem.47":6,"stat.useItem.155":198,"stat.useItem.76":339,"stat.leaveGame":22,"stat.diveOneCm":110308,"stat.useItem.385":2,"stat.useItem.330":13,"achievement.mineWood":2,"stat.useItem.159":188,"stat.killEntity.Villager":1,"stat.useItem.85":12,"stat.useItem.328":23,"stat.killEntity.Creeper":9,"stat.useItem.383":571,"stat.playOneMinute":1952171,"stat.boatOneCm":30212,"stat.useItem.329":6,"stat.killEntity.Pig":56,"stat.useItem.22":132,"stat.deaths":1,"stat.swimOneCm":155836,"stat.useItem.162":74,"stat.mobKills":76,"stat.horseOneCm":21360,"stat.walkOneCm":1023253,"stat.useItem.145":23,"stat.useItem.35":434,"stat.minecartOneCm":170855,"stat.useItem.276":29,"stat.useItem.27":272,"stat.jump":2328,"stat.useItem.1":16,"stat.useItem.20":168,"stat.useItem.12":84,"stat.useItem.138":2,"stat.useItem.101":5}